Workbook

Sheet Assumptions
A1: ASSUMPTIONS — Doña Fuego Brand Pro Forma (cans + bottles)
A2: Brand entity scope: Doña Fuego cans + Fuego Tequila bottles (Bottles sheet, from historic actuals).
A3: Checkers listing
A4: Stores in Checkers listing | B4: 360 | C4: Final Checkers listing (updated from 300); launch Aug 2026
A5: SKUs in listing | B5: 3 | C5: Margarita, Spicy Margarita, Paloma
A6: Cases per store per SKU (initial fill) | B6: 3 | C6: Per project model
A7: Initial fill (cases) | B7: =B4*B5*B6
A8: October restock (cases) | B8: =1050*B4/300 | C8: Scaled from 1,050 cases at 300 stores (project model)
A9: Reorders
A10: Steady-state store reorder (cases/month) | B10: =600*B4/300 | C10: Scaled from 600 cases/month at 300 stores (project model)
A11: Sixty60 uplift on steady-state reorders | B11: 0.1 | C11: MANAGEMENT ESTIMATE (conservative): on-demand delivery adds 10% to monthly reorders
A12: Steady-state incl. Sixty60 (cases/month) | B12: =ROUND(B10*(1+B11),0)
A13: Wholesale price per case (R) | B13: 847.04 | C13: Per project model (R169 4-pack / R49 unit retail)
A14: Payment terms | B14: 30 days from statement
A15: Can COGS build (% of revenue)
A16: Tequila (supply agreement) | B16: 0.18 | C16: Bulk tequila from Doña Distillery under special supply agreement
A17: Packaging (cans, printing, pallets) | B17: 0.16
A18: Co-pack production | B18: 0.12
A19: Distribution (FAL) | B19: 0.04
A20: SARS Excise | B20: 0.2
A21: Total can COGS ratio | B21: =SUM(B16:B20)
A22: Operating costs
A23: Legal & admin (R/month) | B23: 10000 | C23: Per project model
A24: Launch cost scaling vs project model | B24: =B4/300 | C24: Applied to 2026 launch cash costs quoted at 300-store scale
A26: Legend: blue = input (edit these) · black = formula · green = link to another sheet · yellow = key assumptions to sense-check

Sheet Bottles
A1: FUEGO TEQUILA BOTTLES — historic sales & projection
A2: Historic revenue per management sales export (bottle & mini, 2023–Jul 2026), received Aug 2026.
A3: Month | B3: 2023 | C3: 2024 | D3: 2025 | E3: 2026 | G3: 2027 (proj)
A4: January | C4: 87354 | D4: 107377.8 | E4: 185865.3 | G4: =(D4+E4)/($D$16+$E$16)*$B$21
A5: February | C5: 7728 | D5: 46920 | E5: 209857.2 | G5: =(D5+E5)/($D$16+$E$16)*$B$21
A6: March | D6: 126617.4 | E6: 260918.59 | G6: =(D6+E6)/($D$16+$E$16)*$B$21
A7: April | C7: 21931.51 | D7: 663918 | E7: 470561.32 | G7: =(D7+E7)/($D$16+$E$16)*$B$21
A8: May | C8: 1895.8 | D8: 168670.5 | E8: 167687.8 | G8: =(D8+E8)/($D$16+$E$16)*$B$21
A9: June | C9: 68533.21 | D9: 98574.11 | E9: 60059.82 | G9: =(D9+E9)/($D$16+$E$16)*$B$21
A10: July | C10: 36027.3 | D10: 266641.05 | E10: 188654.34 | G10: =(D10+E10)/($D$16+$E$16)*$B$21
A11: August | C11: 5796 | D11: 44441.56 | E11: =D11*$B$19 | G11: =(D11+E11)/($D$16+$E$16)*$B$21
A12: September | B12: 1334 | C12: 46252.59 | D12: 65847.11 | E12: =D12*$B$19 | G12: =(D12+E12)/($D$16+$E$16)*$B$21
A13: October | B13: 2894 | C13: 530949.81 | D13: 63268.38 | E13: =D13*$B$19 | G13: =(D13+E13)/($D$16+$E$16)*$B$21
A14: November | C14: 81964.75 | D14: 257848.55 | E14: =D14*$B$19 | G14: =(D14+E14)/($D$16+$E$16)*$B$21
A15: December | B15: 21919 | C15: 138333.09 | D15: 35332.6 | E15: =D15*$B$19 | G15: =(D15+E15)/($D$16+$E$16)*$B$21
A16: Annual total | B16: =SUM(B4:B15) | C16: =SUM(C4:C15) | D16: =SUM(D4:D15) | E16: =SUM(E4:E15) | G16: =SUM(G4:G15)
A18: Projection assumptions
A19: YoY growth (Jan-Jul 26 vs Jan-Jul 25) | B19: =SUM(E4:E10)/SUM(D4:D10) | C19: Applied to 2025 actuals for Aug-Dec 2026
A20: 2027 growth on 2026 | B20: 0.05 | C20: CONSERVATIVE vs +89% (2025) and +4.4% YTD (2026)
A21: 2027 total | B21: =E16*(1+B20)
A22: Bottle gross margin % | B22: 0.3 | C22: PLACEHOLDER matching cans — awaiting bottle cost data from management
A24: 2026 cells Aug-Dec are projections (2025 month x B19); 2027 monthly = blended 2025+2026 seasonality x B21.

Sheet P&L
A1: P&L (ACCRUAL) — Doña Fuego cans + Fuego Tequila bottles
A3: Month | B3: 46174 | C3: 46204 | D3: 46235 | E3: 46266 | F3: 46296 | G3: 46327 | H3: 46357 | I3: 46388 | J3: 46419 | K3: 46447 | L3: 46478 | M3: 46508 | N3: 46539 | O3: 46569 | P3: 46600 | Q3: 46631 | R3: 46661 | S3: 46692 | T3: 46722 | U3: TOTAL
A4: Cases delivered (cans) | B4: 0 | C4: 0 | D4: =Assumptions!B7 | E4: 0 | F4: =Assumptions!B8 | G4: =Assumptions!B12 | H4: =Assumptions!B12 | I4: =Assumptions!B12 | J4: =Assumptions!B12 | K4: =Assumptions!B12 | L4: =Assumptions!B12 | M4: =Assumptions!B12 | N4: =Assumptions!B12 | O4: =Assumptions!B12 | P4: =Assumptions!B12 | Q4: =Assumptions!B12 | R4: =Assumptions!B12 | S4: =Assumptions!B12 | T4: =Assumptions!B12 | U4: =SUM(B4:T4)
A5: Can revenue | B5: =B4*Assumptions!$B$13 | C5: =C4*Assumptions!$B$13 | D5: =D4*Assumptions!$B$13 | E5: =E4*Assumptions!$B$13 | F5: =F4*Assumptions!$B$13 | G5: =G4*Assumptions!$B$13 | H5: =H4*Assumptions!$B$13 | I5: =I4*Assumptions!$B$13 | ... T5: =T4*Assumptions!$B$13 | U5: =SUM(B5:T5)
A6: Bottle revenue | B6: =Bottles!E9 | C6: =Bottles!E10 | D6: =Bottles!E11 | E6: =Bottles!E12 | F6: =Bottles!E13 | G6: =Bottles!E14 | H6: =Bottles!E15 | I6: =Bottles!G4 | J6: =Bottles!G5 | K6: =Bottles!G6 | L6: =Bottles!G7 | M6: =Bottles!G8 | N6: =Bottles!G9 | O6: =Bottles!G10 | P6: =Bottles!G11 | Q6: =Bottles!G12 | R6: =Bottles!G13 | S6: =Bottles!G14 | T6: =Bottles!G15 | U6: =SUM(B6:T6)
A7: Total revenue | B7: =B5+B6 | C7: =C5+C6 | D7: =D5+D6 | E7: =E5+E6 | F7: =F5+F6 | G7: =G5+G6 | H7: =H5+H6 | I7: =I5+I6 | ... T7: =T5+T6 | U7: =SUM(B7:T7)
A8: Can COGS | B8: =-B5*Assumptions!$B$21 | C8: =-C5*Assumptions!$B$21 | D8: =-D5*Assumptions!$B$21 | E8: =-E5*Assumptions!$B$21 | F8: =-F5*Assumptions!$B$21 | G8: =-G5*Assumptions!$B$21 | H8: =-H5*Assumptions!$B$21 | I8: =-I5*Assumptions!$B$21 | ... T8: =-T5*Assumptions!$B$21 | U8: =SUM(B8:T8)
A9: Bottle COGS | B9: =-B6*(1-Bottles!$B$22) | C9: =-C6*(1-Bottles!$B$22) | D9: =-D6*(1-Bottles!$B$22) | E9: =-E6*(1-Bottles!$B$22) | F9: =-F6*(1-Bottles!$B$22) | G9: =-G6*(1-Bottles!$B$22) | H9: =-H6*(1-Bottles!$B$22) | I9: =-I6*(1-Bottles!$B$22) | ... T9: =-T6*(1-Bottles!$B$22) | U9: =SUM(B9:T9)
A10: Gross margin | B10: =B7+B8+B9 | C10: =C7+C8+C9 | D10: =D7+D8+D9 | E10: =E7+E8+E9 | F10: =F7+F8+F9 | G10: =G7+G8+G9 | H10: =H7+H8+H9 | I10: =I7+I8+I9 | ... T10: =T7+T8+T9 | U10: =SUM(B10:T10)
A11: Gross margin % | B11: =IF(B7=0,0,B10/B7) | C11: =IF(C7=0,0,C10/C7) | D11: =IF(D7=0,0,D10/D7) | E11: =IF(E7=0,0,E10/E7) | F11: =IF(F7=0,0,F10/F7) | G11: =IF(G7=0,0,G10/G7) | H11: =IF(H7=0,0,H10/H7) | I11: =IF(I7=0,0,I10/I7) | ... T11: =IF(T7=0,0,T10/T7) | U11: =U10/U7
A12: Opex (legal & admin) | B12: =-Assumptions!$B$23 | C12: =-Assumptions!$B$23 | D12: =-Assumptions!$B$23 | E12: =-Assumptions!$B$23 | F12: =-Assumptions!$B$23 | G12: =-Assumptions!$B$23 | H12: =-Assumptions!$B$23 | I12: =-Assumptions!$B$23 | ... T12: =-Assumptions!$B$23 | U12: =SUM(B12:T12)
A13: EBITDA | B13: =B10+B12 | C13: =C10+C12 | D13: =D10+D12 | E13: =E10+E12 | F13: =F10+F12 | G13: =G10+G12 | H13: =H10+H12 | I13: =I10+I12 | ... T13: =T10+T12 | U13: =SUM(B13:T13)
A14: EBITDA % | B14: =IF(B7=0,0,B13/B7) | C14: =IF(C7=0,0,C13/C7) | D14: =IF(D7=0,0,D13/D7) | E14: =IF(E7=0,0,E13/E7) | F14: =IF(F7=0,0,F13/F7) | G14: =IF(G7=0,0,G13/G7) | H14: =IF(H7=0,0,H13/H7) | I14: =IF(I7=0,0,I13/I7) | ... T14: =IF(T7=0,0,T13/T7) | U14: =U13/U7

Sheet Cashflow
A1: CASHFLOW (CASH BASIS) — brand entity
A3: Month | B3: 46174 | C3: 46204 | D3: 46235 | E3: 46266 | F3: 46296 | G3: 46327 | H3: 46357 | I3: 46388 | J3: 46419 | K3: 46447 | L3: 46478 | M3: 46508 | N3: 46539 | O3: 46569 | P3: 46600 | Q3: 46631 | R3: 46661 | S3: 46692 | T3: 46722 | U3: TOTAL
A4: Can receipts (revenue +30 days) | B4: 0 | C4: ='P&L'!B5 | D4: ='P&L'!C5 | E4: ='P&L'!D5 | F4: ='P&L'!E5 | G4: ='P&L'!F5 | H4: ='P&L'!G5 | I4: ='P&L'!H5 | J4: ='P&L'!I5 | ... T4: ='P&L'!S5 | U4: =SUM(B4:T4)
A5: Bron Pro (design/brand) | B5: =-103500*Assumptions!$B$24 | D5: =-243800*Assumptions!$B$24 | U5: =SUM(B5:T5)
A6: Sullwaldt printing | C6: =-91066*Assumptions!$B$24 | F6: =-72400*Assumptions!$B$24 | U6: =SUM(B6:T6)
A7: Tiny Keg cans | C7: =-405950*Assumptions!$B$24 | E7: =-319000*Assumptions!$B$24 | U7: =SUM(B7:T7)
A8: Chep pallets | B8: =-14375*Assumptions!$B$24 | U8: =SUM(B8:T8)
A9: FAL distribution | C9: =-51750*Assumptions!$B$24 | F9: =-28000*Assumptions!$B$24 | U9: =SUM(B9:T9)
A10: Tiny Keg production | D10: =-373350*Assumptions!$B$24 | E10: =-293250*Assumptions!$B$24 | U10: =SUM(B10:T10)
A11: SARS excise (launch) | E11: =-630000*Assumptions!$B$24 | G11: =-495571*Assumptions!$B$24 | U11: =SUM(B11:T11)
A12: Legal & admin (2026) | C12: -57500 | U12: =SUM(B12:T12)
A13: Bottles net contribution (GM, cash in month) | B13: ='P&L'!B6*Bottles!$B$22 | C13: ='P&L'!C6*Bottles!$B$22 | D13: ='P&L'!D6*Bottles!$B$22 | E13: ='P&L'!E6*Bottles!$B$22 | F13: ='P&L'!F6*Bottles!$B$22 | G13: ='P&L'!G6*Bottles!$B$22 | H13: ='P&L'!H6*Bottles!$B$22 | I13: ='P&L'!I6*Bottles!$B$22 | ... T13: ='P&L'!T6*Bottles!$B$22 | U13: =SUM(B13:T13)
A14: 2027 recurring can COGS + opex | I14: =-('P&L'!I5*Assumptions!$B$21+Assumptions!$B$23) | J14: =-('P&L'!J5*Assumptions!$B$21+Assumptions!$B$23) | K14: =-('P&L'!K5*Assumptions!$B$21+Assumptions!$B$23) | L14: =-('P&L'!L5*Assumptions!$B$21+Assumptions!$B$23) | M14: =-('P&L'!M5*Assumptions!$B$21+Assumptions!$B$23) | N14: =-('P&L'!N5*Assumptions!$B$21+Assumptions!$B$23) | O14: =-('P&L'!O5*Assumptions!$B$21+Assumptions!$B$23) | P14: =-('P&L'!P5*Assumptions!$B$21+Assumptions!$B$23) | ... T14: =-('P&L'!T5*Assumptions!$B$21+Assumptions!$B$23) | U14: =SUM(B14:T14)
A15: Net monthly cashflow | B15: =SUM(B4:B14) | C15: =SUM(C4:C14) | D15: =SUM(D4:D14) | E15: =SUM(E4:E14) | F15: =SUM(F4:F14) | G15: =SUM(G4:G14) | H15: =SUM(H4:H14) | I15: =SUM(I4:I14) | ... T15: =SUM(T4:T14) | U15: =SUM(B15:T15)
A16: Cumulative cash position | B16: =B15 | C16: =B16+C15 | D16: =C16+D15 | E16: =D16+E15 | F16: =E16+F15 | G16: =F16+G15 | H16: =G16+H15 | I16: =H16+I15 | J16: =I16+J15 | ... T16: =S16+T15
A18: Note: 2026 launch costs are the project model's quoted cash costs, scaled by the store factor (Assumptions!B24); legal retainer unscaled.
A19: Bottles assumed cash-in-month at gross margin; 2027 steady-state can COGS paid in month of delivery.

Sheet Valuation
A1: VALUATION — Doña Fuego brand entity (cans + bottles)
A3: Key metrics (linked to P&L)
A4: 2026 (Jun–Dec) revenue | B4: =SUM('P&L'!B7:H7)
A5: 2026 (Jun–Dec) EBITDA | B5: =SUM('P&L'!B13:H13)
A6: 2027 revenue | B6: =SUM('P&L'!I7:T7)
A7: 2027 EBITDA | B7: =SUM('P&L'!I13:T13)
A9: Method 1: EV/EBITDA on 2027 EBITDA | B9: Low | C9: Base | D9: High
A10: Multiple | B10: 6 | C10: 9 | D10: 12
A11: Enterprise value | B11: =$B$7*B10 | C11: =$B$7*C10 | D11: =$B$7*D10
A13: Method 2: EV/Revenue on 2027 revenue
A14: Multiple | B14: 1 | C14: 1.5 | D14: 2.5
A15: Enterprise value | B15: =$B$6*B14 | C15: =$B$6*C14 | D15: =$B$6*D14
A17: Method 3: simplified DCF (EBITDA as cash proxy)
A18: WACC | B18: 0.22 | C18: 0.18 | D18: 0.15
A19: Exit multiple (2027 EBITDA) | B19: 6 | C19: 8 | D19: 10
A20: Enterprise value (DCF) | B20: =$B$5/(1+B18)^0.25+$B$7/(1+B18)+$B$7*B19/(1+B18)^1.5 | C20: =$B$5/(1+C18)^0.25+$B$7/(1+C18)+$B$7*C19/(1+C18)^1.5 | D20: =$B$5/(1+D18)^0.25+$B$7/(1+D18)+$B$7*D19/(1+D18)^1.5
A22: Blended enterprise value (avg of methods) | B22: =AVERAGE(B11,B15,B20) | C22: =AVERAGE(C11,C15,C20) | D22: =AVERAGE(D11,D15,D20)
A24: Valuation guide for the raise | B24: 15000000 | E24: With bottles modelled off three years of actuals, the ~R15m guide equals the blended LOW case; better-than-flat reorders, new retailers and export remain outside the model.
A26: Same three methods and multiples as the tequila project model, applied to brand-entity economics.

Sheet Summary
A1: SUMMARY — Doña Fuego Brand Pro Forma
A3: Checkers listing | B3: =Assumptions!B4&" stores + Sixty60, Aug 2026"
A4: Opening order (initial fill revenue) | B4: ='P&L'!D5
A5: Bottle revenue (Jun 26 – Dec 27) | B5: ='P&L'!U6
A6: Total revenue, cans + bottles (Jun 26 – Dec 27) | B6: ='P&L'!U7
A7: Total EBITDA (Jun 26 – Dec 27) | B7: ='P&L'!U13
A8: EBITDA margin | B8: ='P&L'!U14
A9: Peak funding need | B9: =MIN(Cashflow!B16:T16)
A10: Ending cash (Dec 27) | B10: =Cashflow!T16
A11: Blended valuation — low | B11: =Valuation!B22
A12: Blended valuation — base | B12: =Valuation!C22
A13: Blended valuation — high | B13: =Valuation!D22
A14: Valuation guide | B14: =Valuation!B24
A16: Not modelled (upside): better-than-flat can reorders, post-exclusivity retailers, export. Bottle margin is a placeholder pending cost data.
